{"gameDetails":{"round":41,"maxRounds":400,"mapWidth":16,"mapHeight":8,"roundIncomeEnergy":5,"buildingPrices":{"DEFENSE":30,"ATTACK":30,"TESLA":300,"ENERGY":20},"buildingsStats":{"DEFENSE":{"health":20,"constructionTime":4,"price":30,"weaponDamage":0,"weaponSpeed":0,"weaponCooldownPeriod":0,"energyGeneratedPerTurn":0,"destroyMultiplier":1,"constructionScore":10},"ATTACK":{"health":5,"constructionTime":2,"price":30,"weaponDamage":5,"weaponSpeed":2,"weaponCooldownPeriod":3,"energyGeneratedPerTurn":0,"destroyMultiplier":1,"constructionScore":4},"TESLA":{"health":5,"constructionTime":11,"price":300,"weaponDamage":20,"weaponSpeed":0,"weaponCooldownPeriod":10,"energyGeneratedPerTurn":0,"destroyMultiplier":10,"constructionScore":20},"ENERGY":{"health":5,"constructionTime":2,"price":20,"weaponDamage":0,"weaponSpeed":0,"weaponCooldownPeriod":0,"energyGeneratedPerTurn":3,"destroyMultiplier":1,"constructionScore":3}}},"players":[{"playerType":"A","energy":195,"health":20,"hitsTaken":16,"score":215},{"playerType":"B","energy":314,"health":100,"hitsTaken":0,"score":2317}],"gameMap":[[{"x":0,"y":0,"buildings":[],"missiles":[],"cellOwner":"A"},{"x":1,"y":0,"buildings":[],"missiles":[],"cellOwner":"A"},{"x":2,"y":0,"buildings":[],"missiles":[{"damage":5,"speed":2,"id":"1fdda969-db8a-4c70-8dd6-1bc4461db535","x":2,"y":0,"playerType":"B"}],"cellOwner":"A"},{"x":3,"y":0,"buildings":[],"missiles":[],"cellOwner":"A"},{"x":4,"y":0,"buildings":[],"missiles":[],"cellOwner":"A"},{"x":5,"y":0,"buildings":[],"missiles":[],"cellOwner":"A"},{"x":6,"y":0,"buildings":[],"missiles":[],"cellOwner":"A"},{"x":7,"y":0,"buildings":[],"missiles":[],"cellOwner":"A"},{"x":8,"y":0,"buildings":[],"missiles":[],"cellOwner":"B"},{"x":9,"y":0,"buildings":[],"missiles":[],"cellOwner":"B"},{"x":10,"y":0,"buildings":[],"missiles":[{"damage":5,"speed":2,"id":"d2e1c3be-1d85-4e39-bfa7-a0bc9da3b308","x":10,"y":0,"playerType":"B"}],"cellOwner":"B"},{"x":11,"y":0,"buildings":[],"missiles":[],"cellOwner":"B"},{"x":12,"y":0,"buildings":[],"missiles":[],"cellOwner":"B"},{"x":13,"y":0,"buildings":[],"missiles":[],"cellOwner":"B"},{"x":14,"y":0,"buildings":[{"health":5,"constructionTimeLeft":-6,"price":30,"weaponDamage":5,"weaponSpeed":2,"weaponCooldownTimeLeft":2,"weaponCooldownPeriod":3,"destroyMultiplier":1,"constructionScore":4,"energyGeneratedPerTurn":0,"maxRange":0,"buildingType":"ATTACK","energyPerShot":0,"x":14,"y":0,"playerType":"B"}],"missiles":[],"cellOwner":"B"},{"x":15,"y":0,"buildings":[{"health":5,"constructionTimeLeft":-40,"price":20,"weaponDamage":0,"weaponSpeed":0,"weaponCooldownTimeLeft":0,"weaponCooldownPeriod":0,"destroyMultiplier":1,"constructionScore":3,"energyGeneratedPerTurn":3,"maxRange":0,"buildingType":"ENERGY","energyPerShot":0,"x":15,"y":0,"playerType":"B"}],"missiles":[],"cellOwner":"B"}],[{"x":0,"y":1,"buildings":[],"missiles":[{"damage":5,"speed":2,"id":"e0d2d6b3-fde4-43d2-a1bb-f5051dc4286e","x":0,"y":1,"playerType":"B"}],"cellOwner":"A"},{"x":1,"y":1,"buildings":[],"missiles":[{"damage":5,"speed":2,"id":"1c9fee23-0943-42c2-99eb-fbd72d60e736","x":1,"y":1,"playerType":"B"}],"cellOwner":"A"},{"x":2,"y":1,"buildings":[],"missiles":[{"damage":5,"speed":2,"id":"cdfd5097-0d60-4723-8353-7723a3f13491","x":2,"y":1,"playerType":"B"}],"cellOwner":"A"},{"x":3,"y":1,"buildings":[],"missiles":[],"cellOwner":"A"},{"x":4,"y":1,"buildings":[],"missiles":[{"damage":5,"speed":2,"id":"3b1459a6-db68-46d1-b8ea-7b0dcdf98ef3","x":4,"y":1,"playerType":"B"}],"cellOwner":"A"},{"x":5,"y":1,"buildings":[],"missiles":[{"damage":5,"speed":2,"id":"31435688-5a4b-4b8d-b27c-c839fd8cd22f","x":5,"y":1,"playerType":"B"}],"cellOwner":"A"},{"x":6,"y":1,"buildings":[],"missiles":[],"cellOwner":"A"},{"x":7,"y":1,"buildings":[],"missiles":[{"damage":5,"speed":2,"id":"50eccc6e-29e5-4253-9665-20698e11f3d6","x":7,"y":1,"playerType":"B"}],"cellOwner":"A"},{"x":8,"y":1,"buildings":[{"health":20,"constructionTimeLeft":-11,"price":30,"weaponDamage":0,"weaponSpeed":0,"weaponCooldownTimeLeft":0,"weaponCooldownPeriod":0,"destroyMultiplier":1,"constructionScore":10,"energyGeneratedPerTurn":0,"maxRange":0,"buildingType":"DEFENSE","energyPerShot":0,"x":8,"y":1,"playerType":"B"}],"missiles":[{"damage":5,"speed":2,"id":"25fe3b6c-e672-436b-a2a8-1cc021c1211b","x":8,"y":1,"playerType":"B"}],"cellOwner":"B"},{"x":9,"y":1,"buildings":[{"health":5,"constructionTimeLeft":-12,"price":30,"weaponDamage":5,"weaponSpeed":2,"weaponCooldownTimeLeft":0,"weaponCooldownPeriod":3,"destroyMultiplier":1,"constructionScore":4,"energyGeneratedPerTurn":0,"maxRange":0,"buildingType":"ATTACK","energyPerShot":0,"x":9,"y":1,"playerType":"B"}],"missiles":[],"cellOwner":"B"},{"x":10,"y":1,"buildings":[{"health":5,"constructionTimeLeft":-11,"price":30,"weaponDamage":5,"weaponSpeed":2,"weaponCooldownTimeLeft":1,"weaponCooldownPeriod":3,"destroyMultiplier":1,"constructionScore":4,"energyGeneratedPerTurn":0,"maxRange":0,"buildingType":"ATTACK","energyPerShot":0,"x":10,"y":1,"playerType":"B"}],"missiles":[{"damage":5,"speed":2,"id":"42838daa-cc76-406b-9d2b-1d6e025580f9","x":10,"y":1,"playerType":"B"}],"cellOwner":"B"},{"x":11,"y":1,"buildings":[{"health":5,"constructionTimeLeft":-10,"price":30,"weaponDamage":5,"weaponSpeed":2,"weaponCooldownTimeLeft":2,"weaponCooldownPeriod":3,"destroyMultiplier":1,"constructionScore":4,"energyGeneratedPerTurn":0,"maxRange":0,"buildingType":"ATTACK","energyPerShot":0,"x":11,"y":1,"playerType":"B"}],"missiles":[],"cellOwner":"B"},{"x":12,"y":1,"buildings":[{"health":5,"constructionTimeLeft":-9,"price":30,"weaponDamage":5,"weaponSpeed":2,"weaponCooldownTimeLeft":3,"weaponCooldownPeriod":3,"destroyMultiplier":1,"constructionScore":4,"energyGeneratedPerTurn":0,"maxRange":0,"buildingType":"ATTACK","energyPerShot":0,"x":12,"y":1,"playerType":"B"}],"missiles":[],"cellOwner":"B"},{"x":13,"y":1,"buildings":[{"health":5,"constructionTimeLeft":-8,"price":30,"weaponDamage":5,"weaponSpeed":2,"weaponCooldownTimeLeft":0,"weaponCooldownPeriod":3,"destroyMultiplier":1,"constructionScore":4,"energyGeneratedPerTurn":0,"maxRange":0,"buildingType":"ATTACK","energyPerShot":0,"x":13,"y":1,"playerType":"B"}],"missiles":[],"cellOwner":"B"},{"x":14,"y":1,"buildings":[{"health":5,"constructionTimeLeft":-7,"price":30,"weaponDamage":5,"weaponSpeed":2,"weaponCooldownTimeLeft":1,"weaponCooldownPeriod":3,"destroyMultiplier":1,"constructionScore":4,"energyGeneratedPerTurn":0,"maxRange":0,"buildingType":"ATTACK","energyPerShot":0,"x":14,"y":1,"playerType":"B"}],"missiles":[],"cellOwner":"B"},{"x":15,"y":1,"buildings":[{"health":5,"constructionTimeLeft":-37,"price":20,"weaponDamage":0,"weaponSpeed":0,"weaponCooldownTimeLeft":0,"weaponCooldownPeriod":0,"destroyMultiplier":1,"constructionScore":3,"energyGeneratedPerTurn":3,"maxRange":0,"buildingType":"ENERGY","energyPerShot":0,"x":15,"y":1,"playerType":"B"}],"missiles":[],"cellOwner":"B"}],[{"x":0,"y":2,"buildings":[],"missiles":[],"cellOwner":"A"},{"x":1,"y":2,"buildings":[],"missiles":[],"cellOwner":"A"},{"x":2,"y":2,"buildings":[],"missiles":[],"cellOwner":"A"},{"x":3,"y":2,"buildings":[],"missiles":[],"cellOwner":"A"},{"x":4,"y":2,"buildings":[],"missiles":[{"damage":5,"speed":2,"id":"727432f7-3cbd-4359-a7bb-37bd65113811","x":4,"y":2,"playerType":"B"}],"cellOwner":"A"},{"x":5,"y":2,"buildings":[],"missiles":[],"cellOwner":"A"},{"x":6,"y":2,"buildings":[],"missiles":[],"cellOwner":"A"},{"x":7,"y":2,"buildings":[],"missiles":[],"cellOwner":"A"},{"x":8,"y":2,"buildings":[],"missiles":[],"cellOwner":"B"},{"x":9,"y":2,"buildings":[],"missiles":[],"cellOwner":"B"},{"x":10,"y":2,"buildings":[],"missiles":[],"cellOwner":"B"},{"x":11,"y":2,"buildings":[],"missiles":[],"cellOwner":"B"},{"x":12,"y":2,"buildings":[],"missiles":[{"damage":5,"speed":2,"id":"3275ae42-a2d4-43cc-b4f1-296d46ef85a2","x":12,"y":2,"playerType":"B"}],"cellOwner":"B"},{"x":13,"y":2,"buildings":[],"missiles":[],"cellOwner":"B"},{"x":14,"y":2,"buildings":[{"health":5,"constructionTimeLeft":-17,"price":30,"weaponDamage":5,"weaponSpeed":2,"weaponCooldownTimeLeft":3,"weaponCooldownPeriod":3,"destroyMultiplier":1,"constructionScore":4,"energyGeneratedPerTurn":0,"maxRange":0,"buildingType":"ATTACK","energyPerShot":0,"x":14,"y":2,"playerType":"B"}],"missiles":[],"cellOwner":"B"},{"x":15,"y":2,"buildings":[{"health":5,"constructionTimeLeft":-35,"price":20,"weaponDamage":0,"weaponSpeed":0,"weaponCooldownTimeLeft":0,"weaponCooldownPeriod":0,"destroyMultiplier":1,"constructionScore":3,"energyGeneratedPerTurn":3,"maxRange":0,"buildingType":"ENERGY","energyPerShot":0,"x":15,"y":2,"playerType":"B"}],"missiles":[],"cellOwner":"B"}],[{"x":0,"y":3,"buildings":[],"missiles":[],"cellOwner":"A"},{"x":1,"y":3,"buildings":[],"missiles":[],"cellOwner":"A"},{"x":2,"y":3,"buildings":[],"missiles":[],"cellOwner":"A"},{"x":3,"y":3,"buildings":[],"missiles":[],"cellOwner":"A"},{"x":4,"y":3,"buildings":[],"missiles":[],"cellOwner":"A"},{"x":5,"y":3,"buildings":[],"missiles":[],"cellOwner":"A"},{"x":6,"y":3,"buildings":[],"missiles":[],"cellOwner":"A"},{"x":7,"y":3,"buildings":[],"missiles":[],"cellOwner":"A"},{"x":8,"y":3,"buildings":[],"missiles":[],"cellOwner":"B"},{"x":9,"y":3,"buildings":[],"missiles":[],"cellOwner":"B"},{"x":10,"y":3,"buildings":[],"missiles":[],"cellOwner":"B"},{"x":11,"y":3,"buildings":[],"missiles":[],"cellOwner":"B"},{"x":12,"y":3,"buildings":[],"missiles":[],"cellOwner":"B"},{"x":13,"y":3,"buildings":[],"missiles":[],"cellOwner":"B"},{"x":14,"y":3,"buildings":[],"missiles":[],"cellOwner":"B"},{"x":15,"y":3,"buildings":[{"health":5,"constructionTimeLeft":-33,"price":20,"weaponDamage":0,"weaponSpeed":0,"weaponCooldownTimeLeft":0,"weaponCooldownPeriod":0,"destroyMultiplier":1,"constructionScore":3,"energyGeneratedPerTurn":3,"maxRange":0,"buildingType":"ENERGY","energyPerShot":0,"x":15,"y":3,"playerType":"B"}],"missiles":[],"cellOwner":"B"}],[{"x":0,"y":4,"buildings":[],"missiles":[{"damage":5,"speed":2,"id":"0b803e0c-e0f1-4b8d-ba1c-ea11f74cfb70","x":0,"y":4,"playerType":"B"}],"cellOwner":"A"},{"x":1,"y":4,"buildings":[],"missiles":[],"cellOwner":"A"},{"x":2,"y":4,"buildings":[],"missiles":[],"cellOwner":"A"},{"x":3,"y":4,"buildings":[],"missiles":[],"cellOwner":"A"},{"x":4,"y":4,"buildings":[],"missiles":[],"cellOwner":"A"},{"x":5,"y":4,"buildings":[],"missiles":[],"cellOwner":"A"},{"x":6,"y":4,"buildings":[],"missiles":[],"cellOwner":"A"},{"x":7,"y":4,"buildings":[],"missiles":[],"cellOwner":"A"},{"x":8,"y":4,"buildings":[],"missiles":[{"damage":5,"speed":2,"id":"166ccfdd-a999-41ed-a587-5d7f9cf2482f","x":8,"y":4,"playerType":"B"}],"cellOwner":"B"},{"x":9,"y":4,"buildings":[],"missiles":[],"cellOwner":"B"},{"x":10,"y":4,"buildings":[],"missiles":[],"cellOwner":"B"},{"x":11,"y":4,"buildings":[],"missiles":[],"cellOwner":"B"},{"x":12,"y":4,"buildings":[],"missiles":[],"cellOwner":"B"},{"x":13,"y":4,"buildings":[],"missiles":[],"cellOwner":"B"},{"x":14,"y":4,"buildings":[{"health":5,"constructionTimeLeft":-15,"price":30,"weaponDamage":5,"weaponSpeed":2,"weaponCooldownTimeLeft":1,"weaponCooldownPeriod":3,"destroyMultiplier":1,"constructionScore":4,"energyGeneratedPerTurn":0,"maxRange":0,"buildingType":"ATTACK","energyPerShot":0,"x":14,"y":4,"playerType":"B"}],"missiles":[],"cellOwner":"B"},{"x":15,"y":4,"buildings":[{"health":5,"constructionTimeLeft":-31,"price":20,"weaponDamage":0,"weaponSpeed":0,"weaponCooldownTimeLeft":0,"weaponCooldownPeriod":0,"destroyMultiplier":1,"constructionScore":3,"energyGeneratedPerTurn":3,"maxRange":0,"buildingType":"ENERGY","energyPerShot":0,"x":15,"y":4,"playerType":"B"}],"missiles":[],"cellOwner":"B"}],[{"x":0,"y":5,"buildings":[],"missiles":[],"cellOwner":"A"},{"x":1,"y":5,"buildings":[],"missiles":[],"cellOwner":"A"},{"x":2,"y":5,"buildings":[],"missiles":[],"cellOwner":"A"},{"x":3,"y":5,"buildings":[],"missiles":[],"cellOwner":"A"},{"x":4,"y":5,"buildings":[],"missiles":[],"cellOwner":"A"},{"x":5,"y":5,"buildings":[],"missiles":[],"cellOwner":"A"},{"x":6,"y":5,"buildings":[],"missiles":[{"damage":5,"speed":2,"id":"21aac7a8-e348-4130-867e-db3a8f1556aa","x":6,"y":5,"playerType":"B"}],"cellOwner":"A"},{"x":7,"y":5,"buildings":[],"missiles":[],"cellOwner":"A"},{"x":8,"y":5,"buildings":[],"missiles":[],"cellOwner":"B"},{"x":9,"y":5,"buildings":[],"missiles":[],"cellOwner":"B"},{"x":10,"y":5,"buildings":[],"missiles":[],"cellOwner":"B"},{"x":11,"y":5,"buildings":[],"missiles":[],"cellOwner":"B"},{"x":12,"y":5,"buildings":[],"missiles":[],"cellOwner":"B"},{"x":13,"y":5,"buildings":[],"missiles":[],"cellOwner":"B"},{"x":14,"y":5,"buildings":[{"health":5,"constructionTimeLeft":-16,"price":30,"weaponDamage":5,"weaponSpeed":2,"weaponCooldownTimeLeft":0,"weaponCooldownPeriod":3,"destroyMultiplier":1,"constructionScore":4,"energyGeneratedPerTurn":0,"maxRange":0,"buildingType":"ATTACK","energyPerShot":0,"x":14,"y":5,"playerType":"B"}],"missiles":[],"cellOwner":"B"},{"x":15,"y":5,"buildings":[{"health":5,"constructionTimeLeft":-30,"price":20,"weaponDamage":0,"weaponSpeed":0,"weaponCooldownTimeLeft":0,"weaponCooldownPeriod":0,"destroyMultiplier":1,"constructionScore":3,"energyGeneratedPerTurn":3,"maxRange":0,"buildingType":"ENERGY","energyPerShot":0,"x":15,"y":5,"playerType":"B"}],"missiles":[],"cellOwner":"B"}],[{"x":0,"y":6,"buildings":[{"health":5,"constructionTimeLeft":-36,"price":30,"weaponDamage":0,"weaponSpeed":0,"weaponCooldownTimeLeft":0,"weaponCooldownPeriod":0,"destroyMultiplier":1,"constructionScore":10,"energyGeneratedPerTurn":0,"maxRange":0,"buildingType":"DEFENSE","energyPerShot":0,"x":0,"y":6,"playerType":"A"}],"missiles":[],"cellOwner":"A"},{"x":1,"y":6,"buildings":[],"missiles":[],"cellOwner":"A"},{"x":2,"y":6,"buildings":[],"missiles":[{"damage":5,"speed":2,"id":"b6b65b09-9370-4cd2-bcd8-48b35c935861","x":2,"y":6,"playerType":"B"}],"cellOwner":"A"},{"x":3,"y":6,"buildings":[],"missiles":[{"damage":5,"speed":2,"id":"5f63544a-1637-4bc7-96e5-4b2c6744fdfa","x":3,"y":6,"playerType":"B"}],"cellOwner":"A"},{"x":4,"y":6,"buildings":[],"missiles":[],"cellOwner":"A"},{"x":5,"y":6,"buildings":[],"missiles":[],"cellOwner":"A"},{"x":6,"y":6,"buildings":[],"missiles":[{"damage":5,"speed":2,"id":"e8f2a98a-2a51-4113-b4b2-e9ff6042537e","x":6,"y":6,"playerType":"B"}],"cellOwner":"A"},{"x":7,"y":6,"buildings":[],"missiles":[],"cellOwner":"A"},{"x":8,"y":6,"buildings":[{"health":20,"constructionTimeLeft":-2,"price":30,"weaponDamage":0,"weaponSpeed":0,"weaponCooldownTimeLeft":0,"weaponCooldownPeriod":0,"destroyMultiplier":1,"constructionScore":10,"energyGeneratedPerTurn":0,"maxRange":0,"buildingType":"DEFENSE","energyPerShot":0,"x":8,"y":6,"playerType":"B"}],"missiles":[],"cellOwner":"B"},{"x":9,"y":6,"buildings":[{"health":5,"constructionTimeLeft":-3,"price":30,"weaponDamage":5,"weaponSpeed":2,"weaponCooldownTimeLeft":1,"weaponCooldownPeriod":3,"destroyMultiplier":1,"constructionScore":4,"energyGeneratedPerTurn":0,"maxRange":0,"buildingType":"ATTACK","energyPerShot":0,"x":9,"y":6,"playerType":"B"}],"missiles":[{"damage":5,"speed":2,"id":"a07ea82d-3239-45f5-bb07-bb4e3e90a04e","x":9,"y":6,"playerType":"B"}],"cellOwner":"B"},{"x":10,"y":6,"buildings":[{"health":5,"constructionTimeLeft":-2,"price":30,"weaponDamage":5,"weaponSpeed":2,"weaponCooldownTimeLeft":2,"weaponCooldownPeriod":3,"destroyMultiplier":1,"constructionScore":4,"energyGeneratedPerTurn":0,"maxRange":0,"buildingType":"ATTACK","energyPerShot":0,"x":10,"y":6,"playerType":"B"}],"missiles":[{"damage":5,"speed":2,"id":"673a4033-60f7-4053-8cef-6e6d599b0edc","x":10,"y":6,"playerType":"B"}],"cellOwner":"B"},{"x":11,"y":6,"buildings":[{"health":5,"constructionTimeLeft":-1,"price":30,"weaponDamage":5,"weaponSpeed":2,"weaponCooldownTimeLeft":3,"weaponCooldownPeriod":3,"destroyMultiplier":1,"constructionScore":4,"energyGeneratedPerTurn":0,"maxRange":0,"buildingType":"ATTACK","energyPerShot":0,"x":11,"y":6,"playerType":"B"}],"missiles":[],"cellOwner":"B"},{"x":12,"y":6,"buildings":[{"health":5,"constructionTimeLeft":0,"price":30,"weaponDamage":5,"weaponSpeed":2,"weaponCooldownTimeLeft":0,"weaponCooldownPeriod":3,"destroyMultiplier":1,"constructionScore":4,"energyGeneratedPerTurn":0,"maxRange":0,"buildingType":"ATTACK","energyPerShot":0,"x":12,"y":6,"playerType":"B"}],"missiles":[],"cellOwner":"B"},{"x":13,"y":6,"buildings":[],"missiles":[],"cellOwner":"B"},{"x":14,"y":6,"buildings":[{"health":5,"constructionTimeLeft":-18,"price":30,"weaponDamage":5,"weaponSpeed":2,"weaponCooldownTimeLeft":2,"weaponCooldownPeriod":3,"destroyMultiplier":1,"constructionScore":4,"energyGeneratedPerTurn":0,"maxRange":0,"buildingType":"ATTACK","energyPerShot":0,"x":14,"y":6,"playerType":"B"}],"missiles":[],"cellOwner":"B"},{"x":15,"y":6,"buildings":[{"health":5,"constructionTimeLeft":-29,"price":20,"weaponDamage":0,"weaponSpeed":0,"weaponCooldownTimeLeft":0,"weaponCooldownPeriod":0,"destroyMultiplier":1,"constructionScore":3,"energyGeneratedPerTurn":3,"maxRange":0,"buildingType":"ENERGY","energyPerShot":0,"x":15,"y":6,"playerType":"B"}],"missiles":[],"cellOwner":"B"}],[{"x":0,"y":7,"buildings":[],"missiles":[],"cellOwner":"A"},{"x":1,"y":7,"buildings":[],"missiles":[],"cellOwner":"A"},{"x":2,"y":7,"buildings":[],"missiles":[],"cellOwner":"A"},{"x":3,"y":7,"buildings":[],"missiles":[],"cellOwner":"A"},{"x":4,"y":7,"buildings":[],"missiles":[{"damage":5,"speed":2,"id":"6716ae1a-d2ca-4c6d-9449-865ef83b0d67","x":4,"y":7,"playerType":"B"}],"cellOwner":"A"},{"x":5,"y":7,"buildings":[],"missiles":[],"cellOwner":"A"},{"x":6,"y":7,"buildings":[],"missiles":[],"cellOwner":"A"},{"x":7,"y":7,"buildings":[],"missiles":[],"cellOwner":"A"},{"x":8,"y":7,"buildings":[],"missiles":[],"cellOwner":"B"},{"x":9,"y":7,"buildings":[],"missiles":[],"cellOwner":"B"},{"x":10,"y":7,"buildings":[],"missiles":[],"cellOwner":"B"},{"x":11,"y":7,"buildings":[],"missiles":[],"cellOwner":"B"},{"x":12,"y":7,"buildings":[],"missiles":[{"damage":5,"speed":2,"id":"ac71ee96-eba0-4326-b626-0c34426b63bb","x":12,"y":7,"playerType":"B"}],"cellOwner":"B"},{"x":13,"y":7,"buildings":[],"missiles":[],"cellOwner":"B"},{"x":14,"y":7,"buildings":[{"health":5,"constructionTimeLeft":-5,"price":30,"weaponDamage":5,"weaponSpeed":2,"weaponCooldownTimeLeft":3,"weaponCooldownPeriod":3,"destroyMultiplier":1,"constructionScore":4,"energyGeneratedPerTurn":0,"maxRange":0,"buildingType":"ATTACK","energyPerShot":0,"x":14,"y":7,"playerType":"B"}],"missiles":[],"cellOwner":"B"},{"x":15,"y":7,"buildings":[{"health":5,"constructionTimeLeft":-28,"price":20,"weaponDamage":0,"weaponSpeed":0,"weaponCooldownTimeLeft":0,"weaponCooldownPeriod":0,"destroyMultiplier":1,"constructionScore":3,"energyGeneratedPerTurn":3,"maxRange":0,"buildingType":"ENERGY","energyPerShot":0,"x":15,"y":7,"playerType":"B"}],"missiles":[],"cellOwner":"B"}]],"teslaHitList":[]}